[
  {
    "publisherId": "edaily",
    "publisherName": "이데일리",
    "specTitle": "기업",
    "categories": [
      "industry"
    ],
    "specUrl": "http://rss.edaily.co.kr/enterprise_news.xml",
    "title": "'개인정보유출' 쿠팡, 4분기 실적은…김범석 메시지 촉각",
    "partialText": "지난해 말 대규모 개인정보 유출 사태로 논란을 빚은 쿠팡이 27일 새벽 지난해 4분기 실적을 공개한다. 분기마다 사상 최대 매출을 갈아치우며 영향력을 키워온 쿠팡이 위기 속에서도 성장세를 이어갔을지, 김범석 쿠팡Inc 의장의 컨퍼런스콜 메시지에 업계 이목이 집중된다.서울 송파구에 위치한 쿠팡 본사 사진(사진=뉴스1)26일 업계에 따르면 쿠팡Inc는 지난해 ...",
    "date": "2026-02-26T19:00:02.000Z",
    "url": "http://www.edaily.co.kr/news/newspath.asp?newsid=06251686645354456"
  },
  {
    "publisherId": "edaily",
    "publisherName": "이데일리",
    "specTitle": "기업",
    "categories": [
      "industry"
    ],
    "specUrl": "http://rss.edaily.co.kr/enterprise_news.xml",
    "title": "AI 거품론 깼다…엔비디아 역대급 실적에 삼전·닉스 웃음꽃",
    "partialText": "엔비디아가 시장의 예상을 뛰어넘는 사상 최대 실적을 기록하면서 인공지능(AI) 성장이 둔화할 것이라는 거품론을 불식시켰다. AI 칩 수요가 견조한 가운데, 삼성전자와 SK하이닉스 역시 고대역폭메모리(HBM)를 중심으로 호실적을 이어갈 것으로 보인다.(그래픽=김정훈 기자)엔비디아는 25일(현지시간) 장 마감 후 실적발표에서 회계연도 4분기(지난해 11월~올...",
    "date": "2026-02-26T18:39:28.000Z",
    "url": "http://www.edaily.co.kr/news/newspath.asp?newsid=06172966645354456"
  },
  {
    "publisherId": "edaily",
    "publisherName": "이데일리",
    "specTitle": "기업",
    "categories": [
      "industry"
    ],
    "specUrl": "http://rss.edaily.co.kr/enterprise_news.xml",
    "title": "티웨이항공, 작년 영업손실 2654억원…적자폭 확대",
    "partialText": "티웨이항공은 작년 영업손실 2654억원으로 전년 대비 적자폭이 확대됐다고 26일 공시했다. 작년 매출액은 1조7982억원으로 전년 대비 17% 증가했다. 당기순손실은 3395억원으로 역시 손실폭이 확대됐다.작년 4분기 영업손실은 561억원으로 전년 대비 소폭 개선됐다. 매출액은 5239억원으로 전년비 33.3% 증가했다.",
    "date": "2026-02-26T18:14:05.000Z",
    "url": "http://www.edaily.co.kr/news/newspath.asp?newsid=06110646645354456"
  },
  {
    "publisherId": "edaily",
    "publisherName": "이데일리",
    "specTitle": "기업",
    "categories": [
      "industry"
    ],
    "specUrl": "http://rss.edaily.co.kr/enterprise_news.xml",
    "title": "인천공항 면세점 DF1 '롯데'·DF2 '현대' 낙찰",
    "partialText": "인천국제공항 면세점 입찰에서 롯데면세점과 현대면세점이 각각 DF1과 DF2 특허 승인을 받았다. 이번 낙찰로 롯데면세점은 3년 만에 인천공항에 복귀하고, 현대면세점은 사업영역을 대폭 확대하게 됐다.인천공항 면세점(사진=뉴스1)26일 관세청은 ‘관세청 보세판매장 특허심사위원회’ 심사 결과, 인천공항 DF1(화장품·향수/주류·담배) 구역은 호텔롯데(롯데면세점...",
    "date": "2026-02-26T18:09:38.000Z",
    "url": "http://www.edaily.co.kr/news/newspath.asp?newsid=06074566645354456"
  },
  {
    "publisherId": "edaily",
    "publisherName": "이데일리",
    "specTitle": "기업",
    "categories": [
      "industry"
    ],
    "specUrl": "http://rss.edaily.co.kr/enterprise_news.xml",
    "title": "현대 '아이오닉 9' 자동차기자협회 '올해의 차' 선정",
    "partialText": "현대자동차의 아이오닉 9이 한국자동차기자협회가 선정한 2026 대한민국 올해의 차에 올랐다. 한국자동차기자협회는 지난 5일 경기 화성 한국교통안전공단 자동차안전연구원에서 열린 2026 대한민국 올해의 차 최종 심사 결과, 현대자동차 아이오닉 9이 종합 만족도 82.30점(100점 만점)을 획득해 2026 올해의 차에 올랐다고 26일 밝혔다.아이오닉 9이어...",
    "date": "2026-02-26T18:00:03.000Z",
    "url": "http://www.edaily.co.kr/news/newspath.asp?newsid=06031926645354456"
  },
  {
    "publisherId": "edaily",
    "publisherName": "이데일리",
    "specTitle": "기업",
    "categories": [
      "industry"
    ],
    "specUrl": "http://rss.edaily.co.kr/enterprise_news.xml",
    "title": "한국패션협회, 국내 의류제조업 실태조사 발표",
    "partialText": "한국패션협회는 산업통상부의 지원으로 ‘2025년 국내 의류제조업 실태조사’ 결과를 26일 발표했다.  사진=한국패션협회이번 조사는 통계청 승인 국가통계로, 2년 주기 홀수년도에 실시된다. 특히 이번엔 기존 ‘봉제업체 실태조사’에서 ‘의류제조업 실태조사’로 명칭을 변경하고, 조사 방식도 전수조사에서 표본조사 방식으로 전환한 것이 특징이다.또한 산업 구조 변...",
    "date": "2026-02-26T17:59:15.000Z",
    "url": "http://www.edaily.co.kr/news/newspath.asp?newsid=06028646645354456"
  },
  {
    "publisherId": "edaily",
    "publisherName": "이데일리",
    "specTitle": "기업",
    "categories": [
      "industry"
    ],
    "specUrl": "http://rss.edaily.co.kr/enterprise_news.xml",
    "title": "영원무역, 지난해 영업익 5144억…전년比 63%↑",
    "partialText": "영원무역(111770)이 지난해 연결 기준 영업이익 5144억원을 기록해 전년 대비 63% 증가했다고 26일 공시했다.같은 기간 매출은 4조 636억원으로 15.5% 늘었고, 당기순이익은 4280억원으로 45.3% 증가했다. 주력 의류 주문자상표부착생산(OEM) 사업에서 주문이 늘어난 데다 자전거 사업부 스캇(SCOTT)의 적자 폭이 축소되며 수익성이 개...",
    "date": "2026-02-26T17:53:17.000Z",
    "url": "http://www.edaily.co.kr/news/newspath.asp?newsid=05979446645354456"
  },
  {
    "publisherId": "edaily",
    "publisherName": "이데일리",
    "specTitle": "기업",
    "categories": [
      "industry"
    ],
    "specUrl": "http://rss.edaily.co.kr/enterprise_news.xml",
    "title": "로봇 이어 자율주행도 꿈틀…현대차 로보택시 양산 기대감↑",
    "partialText": "구글의 자율주행차 계열사 웨이모가 미국에서 자율주행 로보(무인)택시 광폭행보를 펼치면서 현대자동차의 자율주행 사업에도 탄력이 붙을 것으로 기대된다. 웨이모의 사업 확대에 따라 현대 ‘아이오닉 5’의 공급대수가 늘어나기 때문이다. 현대차가 자회사 ‘모셔널’을 통해 개발 중인 자체 로보택시 서비스의 상용화에도 속도가 붙을 것으로 전망된다.24일 관련 업계에 ...",
    "date": "2026-02-26T17:44:39.000Z",
    "url": "http://www.edaily.co.kr/news/newspath.asp?newsid=05894166645354456"
  },
  {
    "publisherId": "edaily",
    "publisherName": "이데일리",
    "specTitle": "기업",
    "categories": [
      "industry"
    ],
    "specUrl": "http://rss.edaily.co.kr/enterprise_news.xml",
    "title": "'시총 1조달러' 삼성의 진격…이재용 회장 주식재산 첫 40조 돌파",
    "partialText": "이재용 삼성전자 회장의 주식 평가액이 사상 처음 40조을 돌파했다. 삼성전자가 한국 기업사 최초로 시가총액 ‘1조달러 클럽’에 들 정도로 주가가 치솟고 있는 덕이다. 이 회장이 보유한 삼성그룹 내 주요 기업들의 주가 전망이 밝아, 이재용 회장의 주식 재산은 더 불어날 전망이다.이재용 삼성전자 회장. (사진=뉴시스)26일 한국거래소 등에 따르면 이날 종가 ...",
    "date": "2026-02-26T17:09:01.000Z",
    "url": "http://www.edaily.co.kr/news/newspath.asp?newsid=05759686645354456"
  },
  {
    "publisherId": "edaily",
    "publisherName": "이데일리",
    "specTitle": "기업",
    "categories": [
      "industry"
    ],
    "specUrl": "http://rss.edaily.co.kr/enterprise_news.xml",
    "title": "파바·뚜레쥬르, 빵값 내린다…\"연쇄 인하하나\"(종합)",
    "partialText": "국내 대표 제빵업체 파리바게뜨와 뚜레쥬르가 빵 가격을 인하한다. 대형 제빵업계가 가격을 인하하는 것은 정부의 담합 조사에 따른 밀가루값 인하 이후 이번이 처음이다. 이같은 움직임은 정부가 강도 높은 물가 관리 기조를 이어가는 가운데 나왔다. 밀가루를 주원료로 쓰는 라면과 빵·과자의 가격 인하 도미노로 이어질지 이목이 쏠린다.26일 파리바게뜨는 빵과 케이크...",
    "date": "2026-02-26T17:05:11.000Z",
    "url": "http://www.edaily.co.kr/news/newspath.asp?newsid=05749846645354456"
  },
  {
    "publisherId": "edaily",
    "publisherName": "이데일리",
    "specTitle": "기업",
    "categories": [
      "industry"
    ],
    "specUrl": "http://rss.edaily.co.kr/enterprise_news.xml",
    "title": "라면업계, 때 이른 ‘여름면 전쟁’ 불붙었다",
    "partialText": "꽃샘추위가 이어지는 3월 대형마트 라면 매대가 푸른색 패키지로 뒤덮일 예정이다. 라면업체들이 예년보다 서둘러 여름면을 출격시키며, ‘여름 전쟁’의 시작을 앞당긴 탓이다. 26일 라면업계에 따르면 주요 업체들은 3월초부터 여름면 신제품과 리뉴얼 물량을 본격적으로 선보일 예정이다. 계절 제품으로 분류되던 여름면을 사실상 ‘연중 제품’에 가깝게 끌어올린 것이다...",
    "date": "2026-02-26T16:34:20.000Z",
    "url": "http://www.edaily.co.kr/news/newspath.asp?newsid=05592406645354456"
  },
  {
    "publisherId": "edaily",
    "publisherName": "이데일리",
    "specTitle": "기업",
    "categories": [
      "industry"
    ],
    "specUrl": "http://rss.edaily.co.kr/enterprise_news.xml",
    "title": "\"유통규제, 온·오프 특성 반영한 이원적 설계 필요\"",
    "partialText": "“온·오프라인의 경계가 무너진 현 유통시장에 맞도록 규제 체계를 재구성해야 한다.”한국유통법학회가 26일 고려대 CJ법학관에서 '춘계학술대회'를 열고 유통규제에 대한 토론을 진행하고 있다. (사진=김정유 기자)조혜신 한동대 법학부 교수는 26일 고려대 CJ법학관에서 열린 ‘춘계학술대회’에서 “공정거래법과 거래공정화법에 따른 온·오프라인 유통 규제는 각 특...",
    "date": "2026-02-26T16:33:53.000Z",
    "url": "http://www.edaily.co.kr/news/newspath.asp?newsid=05589126645354456"
  },
  {
    "publisherId": "edaily",
    "publisherName": "이데일리",
    "specTitle": "기업",
    "categories": [
      "industry"
    ],
    "specUrl": "http://rss.edaily.co.kr/enterprise_news.xml",
    "title": "SKC, 1조원 규모 유상증자 추진…\"글라스 기판 강화\"",
    "partialText": "SKC가 미래 사업의 성장 가속화와 재무 건전성 강화를 위해 대규모 자금 조달에 나선다.SKC는 26일 이사회를 열고 약 1조원 규모의 유상증자를 결의했다고 밝혔다. 이를 통해 SKC는 글라스기판 등 차세대 소재사업의 실행력을 강화하고 재무구조 개선을 병행해 글로벌 첨단 소재기업으로의 도약을 추진한다. 이날 최대 주주인 SK㈜(지분율 : 40.64%)도 ...",
    "date": "2026-02-26T16:32:43.000Z",
    "url": "http://www.edaily.co.kr/news/newspath.asp?newsid=05582566645354456"
  },
  {
    "publisherId": "edaily",
    "publisherName": "이데일리",
    "specTitle": "기업",
    "categories": [
      "industry"
    ],
    "specUrl": "http://rss.edaily.co.kr/enterprise_news.xml",
    "title": "CJ제일제당, 밀가루 가격 추가 인하…”물가 안정에 적극 동참”",
    "partialText": "CJ제일제당은 밀가루 제품 가격을 평균 5% 추가 인하한다고 26일 밝혔다. 공정위, '밀가루 담합' 7개사 제재최근 업소용(1월 초)·소비자용(2월 초) 밀가루 가격을 각각 평균 4%, 5.5% 내린데 이은 후속 조치다.CJ제일제당측은 “어려운 경영 상황이지만 정부의 물가 안정 기조에 적극 동참하기 위한 취지”라며, “고객과 소비자들의 부담을 조금이나마...",
    "date": "2026-02-26T16:31:54.000Z",
    "url": "http://www.edaily.co.kr/news/newspath.asp?newsid=05579286645354456"
  },
  {
    "publisherId": "edaily",
    "publisherName": "이데일리",
    "specTitle": "기업",
    "categories": [
      "industry"
    ],
    "specUrl": "http://rss.edaily.co.kr/enterprise_news.xml",
    "title": "李대통령 지적에…CJ푸드빌 뚜레쥬르도 빵값 내린다",
    "partialText": "파리바게뜨에 이어 뚜레쥬르도 빵 가격을 인하한다. CJ푸드빌이 운영하는 뚜레쥬르는 빵과 케이크 등 총 17종의 공급가를 평균 8.2% 인하한다고 26일 밝혔다.이 따라 뚜레쥬르의 주요 인기 상품인 △단팥빵과 △마구마구 밤식빵 △生生 생크림식빵 등 빵류 16종의 권장소비자가격은 다음달 12일부터 개당 100~1100원 내려간다. 여기에 더해 인기 캐릭터 케...",
    "date": "2026-02-26T16:25:44.000Z",
    "url": "http://www.edaily.co.kr/news/newspath.asp?newsid=05546486645354456"
  },
  {
    "publisherId": "edaily",
    "publisherName": "이데일리",
    "specTitle": "기업",
    "categories": [
      "industry"
    ],
    "specUrl": "http://rss.edaily.co.kr/enterprise_news.xml",
    "title": "이부진, 아들 서울대 입학식 참석…홍라희도 나란히",
    "partialText": "이부진 호텔신라 사장이 아들 임동현 군의 서울대학교 입학식을 찾아 새로운 출발을 응원했다.(사진=연합뉴스)이 사장은 26일 오전 아들 임 군의 입학식이 열린 서울 관악구 서울대학교 체육관을 방문했다.이날 현장에는 이 사장의 어머니인 홍라희 리움미술관 명예관장도 함께해 손자의 입학을 축하했다.입학식이 끝난 뒤 이 사장은 꽃다발을 들고 있는 임 군의 손을 꼭...",
    "date": "2026-02-26T16:17:40.000Z",
    "url": "http://www.edaily.co.kr/news/newspath.asp?newsid=05503846645354456"
  },
  {
    "publisherId": "edaily",
    "publisherName": "이데일리",
    "specTitle": "기업",
    "categories": [
      "industry"
    ],
    "specUrl": "http://rss.edaily.co.kr/enterprise_news.xml",
    "title": "\"김부장들 짐싼다\"…벼랑 끝 식품업계 `희망퇴직` 러시",
    "partialText": "국내 식품업계가 연초부터 희망퇴직 카드를 다시 꺼내 들었다. 고물가·고금리로 인한 소비 침체 장기화에 경영난을 겪자 ‘몸집 줄이기’에 나선 것이다.26일 관련 업계에 따르면 롯데웰푸드는 45세 이상(1981년 이전 출생자)이면서 근속 10년 이상 임직원을 대상으로 희망퇴직 신청을 받고 있다. 지난해 4월 희망퇴진을 단행한 이후 1년만이다. 급변하는 시장 ...",
    "date": "2026-02-26T16:15:24.000Z",
    "url": "http://www.edaily.co.kr/news/newspath.asp?newsid=05484166645354456"
  },
  {
    "publisherId": "edaily",
    "publisherName": "이데일리",
    "specTitle": "기업",
    "categories": [
      "industry"
    ],
    "specUrl": "http://rss.edaily.co.kr/enterprise_news.xml",
    "title": "한화에어로, 호주 현지 공장서 AS9 자주포 첫 출하",
    "partialText": "한화에어로스페이스가 호주 현지 공장에서 AS9 자주포를 처음으로 출하했다. AS9은 글로벌 자주포 시장에서 점유율 50%가 넘는 K9의 호주 맞춤형 개조 모델이다.한화에어로스페이스는 26일 호주 질롱시 H-ACE에서 AS9 자주포 3문 출하식을 열었다고 밝혔다. 올해 안에 첫 호주산 AS10 탄약운반차도 현지 공장에서 출고될 예정이다. 한화에어로스페이스는...",
    "date": "2026-02-26T15:43:43.000Z",
    "url": "http://www.edaily.co.kr/news/newspath.asp?newsid=05356246645354456"
  },
  {
    "publisherId": "edaily",
    "publisherName": "이데일리",
    "specTitle": "기업",
    "categories": [
      "industry"
    ],
    "specUrl": "http://rss.edaily.co.kr/enterprise_news.xml",
    "title": "현대제철, 탄소저감강판 양산 시작…탄소중립소재 공급 역량 강화",
    "partialText": "현대제철(004020)이 기존 자사 고로 생산 제품보다 탄소배출량을 20% 감축한 탄소저감강판 본격 양산에 들어가며 제품 판매 확대에 나섰다.현대제철은 전기로와 고로의 쇳물을 배합하는 복합프로세스를 세계 최초로 가동해 탄소저감강판 생산에 성공했으며 올해 2월부터 양산을 시작했다고 26일 밝혔다.회사는 2023년 4월부터 당진제철소 기존 전기로를 활용해 탄...",
    "date": "2026-02-26T15:43:18.000Z",
    "url": "http://www.edaily.co.kr/news/newspath.asp?newsid=05352966645354456"
  },
  {
    "publisherId": "edaily",
    "publisherName": "이데일리",
    "specTitle": "기업",
    "categories": [
      "industry"
    ],
    "specUrl": "http://rss.edaily.co.kr/enterprise_news.xml",
    "title": "휴비츠, 검안기기 美 FDA 등록 완료…북미 사업 강화로 매출 회복 기대",
    "partialText": "휴비츠가 검안기기 &lsquo;HRKT-1&rsquo;에 대해 미국 식품의약국(FDA) Class I 의료기기 등록을 이달 19일 완료한 데 이어 캐나다 보건부(Health Canada) Class II 의료기기 라이선스도 취득하며 미주 사업 경쟁력 강화 기반을 마련했다고 26일 밝혔다.이번 승인으로 HRKT-1은 미국과 캐나다에서 모두 유통 및 판매를 ...",
    "date": "2026-02-26T15:22:01.000Z",
    "url": "http://www.edaily.co.kr/news/newspath.asp?newsid=05270966645354456"
  },
  {
    "publisherId": "edaily",
    "publisherName": "이데일리",
    "specTitle": "기업",
    "categories": [
      "industry"
    ],
    "specUrl": "http://rss.edaily.co.kr/enterprise_news.xml",
    "title": "삼성전자 시총, 꿈의 '1조달러 클럽'…한국 기업사 최초",
    "partialText": "삼성전자 시가총액이 1조달러를 돌파했다. ‘1조달러 클럽’은 글로벌 초거대 기업의 상징으로 여겨지는 만큼 신기원을 열었다는 평가가 나온다.26일 시총 분석업체 컴퍼니스마켓캡 등에 따르면 삼성전자는 이날 장중 시총 1조달러를 돌파하며 순위가 14위에서 12위로 2계단 뛰었다. 미국 증시에서 초거대 기업의 상징으로 통하는 시총 1조달러 클럽에 진입한 것이다....",
    "date": "2026-02-26T15:19:17.000Z",
    "url": "http://www.edaily.co.kr/news/newspath.asp?newsid=05261126645354456"
  },
  {
    "publisherId": "edaily",
    "publisherName": "이데일리",
    "specTitle": "기업",
    "categories": [
      "industry"
    ],
    "specUrl": "http://rss.edaily.co.kr/enterprise_news.xml",
    "title": "손경식 회장, 김민석 총리에게 \"노사 안정, 경영 부담 완화\" 건의",
    "partialText": "한국경영자총협회(경총)는 26일 서울 포시즌스호텔 서울에서 ‘국무총리 초청, 경총 간담회 및 K-국정설명’을 개최했다.김민석 국무총리(왼쪽), 손경식 경총 회장이 악수하고 있다. (사진=경총)간담회에는 김민석 국무총리, 문신학 산업통상부 차관 등 정부 관계자와 손경식 경총 회장, 박승희 삼성전자 사장, 이형희 SK 부회장, 정상빈 현대자동차 부사장, 차동...",
    "date": "2026-02-26T14:56:09.000Z",
    "url": "http://www.edaily.co.kr/news/newspath.asp?newsid=05182406645354456"
  },
  {
    "publisherId": "edaily",
    "publisherName": "이데일리",
    "specTitle": "기업",
    "categories": [
      "industry"
    ],
    "specUrl": "http://rss.edaily.co.kr/enterprise_news.xml",
    "title": "“정말 가격이 880원?” 삼겹살 600톤 푼 이마트…‘미끼’는 옛말[르포]",
    "partialText": "“삼겹살 100g에 880원이면 1㎏ 사도 9000원이 안 되잖아요. 요즘 장볼 때마다 한숨이 나오는데, 이런 행사 때 안 오면 손해죠”26일 오전 10시 서울 용산구 이마트(139480) 용산점. 50대 주부 A씨는 개장 20분 전부터 매장 입구에서 카트를 잡고 서 있었다. 이날은 이마트가 다음 달 3일 ‘삼삼데이(삼겹살 데이)’를 앞두고 대규모 할인 ...",
    "date": "2026-02-26T14:54:18.000Z",
    "url": "http://www.edaily.co.kr/news/newspath.asp?newsid=05162726645354456"
  },
  {
    "publisherId": "edaily",
    "publisherName": "이데일리",
    "specTitle": "기업",
    "categories": [
      "industry"
    ],
    "specUrl": "http://rss.edaily.co.kr/enterprise_news.xml",
    "title": "대한항공-英 스카이포츠, 도심 수직이착륙기 운영 플랫폼 개발 파트너십",
    "partialText": "대한항공은 26일 영국 첨단항공모빌리티(AAM) 인프라 전문 기업 스카이포츠 인프라스트럭처(스카이포츠)와 도심항공용 전기수직이착륙기(eVTOL) 통합 운영 플랫폼 개발을 위한 파트너십을 맺었다. 양사는 이날 오후 부산 벡스코에서 열린 ‘드론쇼코리아 2026’ 행사에서 이 같은 내용을 담은 업무협약(MOU)을 체결했다.김경남 대한항공 항공기술연구원장(오른쪽...",
    "date": "2026-02-26T14:48:14.000Z",
    "url": "http://www.edaily.co.kr/news/newspath.asp?newsid=05129926645354456"
  },
  {
    "publisherId": "edaily",
    "publisherName": "이데일리",
    "specTitle": "기업",
    "categories": [
      "industry"
    ],
    "specUrl": "http://rss.edaily.co.kr/enterprise_news.xml",
    "title": "파리바게뜨, 11종 빵값 내린다…밀가루 가격 인하 후 처음",
    "partialText": "상미당홀딩스(옛 SPC)의 베이커리 프랜차이즈 브랜드 파리바게뜨는 빵과 케이크 등 제품 11종의 가격을 다음 달 13일부터 인하한다고 26일 밝혔다.빵 류 대상 품목은 6종으로 100원~1000원 낮춘다. 완제품 권장가격 기준 △단팥빵(1600&rarr;1500원) △소보루빵(1600&rarr;1500원) △슈크림빵(1600&rarr;1500원) △홀그레...",
    "date": "2026-02-26T14:46:21.000Z",
    "url": "http://www.edaily.co.kr/news/newspath.asp?newsid=05123366645354456"
  },
  {
    "publisherId": "edaily",
    "publisherName": "이데일리",
    "specTitle": "기업",
    "categories": [
      "industry"
    ],
    "specUrl": "http://rss.edaily.co.kr/enterprise_news.xml",
    "title": "구내식당 간 `사찰음식`…삼성웰스토리, 선재스님과 협업",
    "partialText": "사찰음식이 ‘구내식당’으로 옮겨갔다. 삼성웰스토리는 오는 3월부터 사찰음식 명장 1호인 선재스님과 손잡고 구내식당에서 사찰음식을 선보이는 ‘셀럽테이블’ 프로모션을 진행한다고 26일 밝혔다.삼성웰스토리에 따르면 최근 몸과 마음의 조화를 추구하는 웰니스(Wellness) 트렌드가 확산함에 따라 이같은 프로모션을 기획했다. 특히 자연에서 온 제철 식재료의 맛을...",
    "date": "2026-02-26T14:35:59.000Z",
    "url": "http://www.edaily.co.kr/news/newspath.asp?newsid=05064326645354456"
  },
  {
    "publisherId": "edaily",
    "publisherName": "이데일리",
    "specTitle": "기업",
    "categories": [
      "industry"
    ],
    "specUrl": "http://rss.edaily.co.kr/enterprise_news.xml",
    "title": "암참·주한미대사관, 美 건국 250주년 ‘프리덤 250’ 협력 MOU",
    "partialText": "주한미국상공회의소(암참)가 주한미국대사관과 미국 건국 250주년 기념 캠페인 ‘프리덤 250(Freedom 250)’ 협력을 위한 양해각서(MOU)를 체결했다.26일 암참에 따르면 두 기관은 올해 한 해 동안 기념 행사와 주요 인사 초청 간담회 등 다양한 공동 프로그램을 추진할 계획이다. 자유와 민주주의라는 공동 가치를 재조명하고 미국의 혁신·기업가정신을...",
    "date": "2026-02-26T14:03:20.000Z",
    "url": "http://www.edaily.co.kr/news/newspath.asp?newsid=04946246645354456"
  },
  {
    "publisherId": "edaily",
    "publisherName": "이데일리",
    "specTitle": "기업",
    "categories": [
      "industry"
    ],
    "specUrl": "http://rss.edaily.co.kr/enterprise_news.xml",
    "title": "웰니스 바람 부는 중화권…亞 침투하는 K애슬레저",
    "partialText": "국내 애슬레저 업계가 아시아 시장 깊숙히 침투하고 있다. 젝시믹스(337930)는 중화권(중국·대만 등)을 중심으로 영향력을 키워가고 있고, 안다르는 싱가포르와 일본 등에서 존재감을 드러내고 있다. 아시아인 몸에 맞는 형태의 제품 스타일과 더불어 최근엔 남성용·고기능성 라인까지 앞세워 차별화를 꾀하고 있다.젝시믹스가 후원한 'NGP 대만 보디빌딩 파이널 ...",
    "date": "2026-02-26T13:51:13.000Z",
    "url": "http://www.edaily.co.kr/news/newspath.asp?newsid=04910166645354456"
  },
  {
    "publisherId": "edaily",
    "publisherName": "이데일리",
    "specTitle": "기업",
    "categories": [
      "industry"
    ],
    "specUrl": "http://rss.edaily.co.kr/enterprise_news.xml",
    "title": "쿠팡이츠, '전통시장·영세매장'만 무료 포장수수료 지원",
    "partialText": "국내 배달 플랫폼 쿠팡이츠가 올해 포장서비스 무료 수수료 프로모션 대상을 전통시장과 매출 하위 20% 영세 매장으로 한정한다. 사진=쿠팡이츠쿠팡이츠는 전통시장 및 상생요금제 매출 규모 하위 20% 이하 매장 대상으로 포장서비스 중개이용료 무료 프로모션을 내년 3월까지 연장한다고 26일 밝혔다.해당 기준 외 입점매장들은 포장 무료 수수료 지원을 다음달까지만...",
    "date": "2026-02-26T11:39:07.000Z",
    "url": "http://www.edaily.co.kr/news/newspath.asp?newsid=04539526645354456"
  },
  {
    "publisherId": "edaily",
    "publisherName": "이데일리",
    "specTitle": "기업",
    "categories": [
      "industry"
    ],
    "specUrl": "http://rss.edaily.co.kr/enterprise_news.xml",
    "title": "성래은 회장 \"K패션 글로벌화 집중, 세계에 한국을 입힐 것\"",
    "partialText": "한국패션협회는 25일 영원무역 명동빌딩에서 2026년도 이사회 및 정기총회를 개최했다고 26일 밝혔다.성래은 한국패션협회장이 25일 영원무역 명동빌딩에서 열린 '2026년 정기총회'에서 인사말을 하고 있다. (사진=한국패션협회)성래은 패션협회장은 개회사를 통해 “지난해 협회 명칭 변경과 창립 40주년을 계기로 산업의 외연을 확장했다면, 2026년은 ‘세계...",
    "date": "2026-02-26T11:24:03.000Z",
    "url": "http://www.edaily.co.kr/news/newspath.asp?newsid=04506726645354456"
  },
  {
    "publisherId": "edaily",
    "publisherName": "이데일리",
    "specTitle": "기업",
    "categories": [
      "industry"
    ],
    "specUrl": "http://rss.edaily.co.kr/enterprise_news.xml",
    "title": "SK바이오사이언스-IDT, 유럽 차세대 독감 백신 프로젝트 수주",
    "partialText": "SK바이오사이언스가 독일 CDMO 기업 IDT 바이오로지카(이하 IDT) 인수 1년 만에 사업 시너지를 본격화하고 있다. 지난해 IDT의 실적 턴어라운드에 성공한 데 이어, 올해는 유럽연합(EU) 산하 기관의 대규모 백신 개발 프로젝트 수행 기업으로 선정되며 가시적인 성과를 이어가고 있다.SK바이오사이언스는 IDT와 함께 유럽 집행위원회(EC) 산하 보건...",
    "date": "2026-02-26T11:18:02.000Z",
    "url": "http://www.edaily.co.kr/news/newspath.asp?newsid=04457526645354456"
  },
  {
    "publisherId": "edaily",
    "publisherName": "이데일리",
    "specTitle": "기업",
    "categories": [
      "industry"
    ],
    "specUrl": "http://rss.edaily.co.kr/enterprise_news.xml",
    "title": "틸 셰어 폭스바겐그룹코리아 대표, 韓수입차협회장 3연임",
    "partialText": "한국수입자동차협회(KAIDA)는 26일 웨스틴 조선호텔에서 총회를 개최하고, 틸 셰어(Till Scheer) 폭스바겐그룹코리아 대표이사 사장을 제17대 KAIDA 회장으로 선임했다고 밝혔다. 틸 셰어 회장은 제15대, 제16대에 이어 3연속 선임되어 향후 2년 간 협회를 이끌게 됐다.틸 셰어 회장은 유럽 및 홍콩, 중국, 일본 등 아시아 시장에서 자동차 ...",
    "date": "2026-02-26T11:14:37.000Z",
    "url": "http://www.edaily.co.kr/news/newspath.asp?newsid=04424726645354456"
  },
  {
    "publisherId": "edaily",
    "publisherName": "이데일리",
    "specTitle": "기업",
    "categories": [
      "industry"
    ],
    "specUrl": "http://rss.edaily.co.kr/enterprise_news.xml",
    "title": "\"하루 12인 한정\"…롯데관광개발, 일본 전통 철판요리 선봬",
    "partialText": "롯데관광개발(032350)은 제주 드림타워 복합리조트 내 그랜드 하얏트 제주 일식당 ‘유메야마’에서 하루 단 12인만을 위한 일본 전통 철판요리인 ‘테판야키 오마카세’를 새롭게 선보인다고 26일 밝혔다. 테판야키 오마카세는 그 날 가장 신선한 식재료를 활용해 셰프가 철판 위에서 즉석으로 재료를 조리해 제공하는 일본 전통 철판요리다. 오마카세는 하루 단 1...",
    "date": "2026-02-26T11:11:17.000Z",
    "url": "http://www.edaily.co.kr/news/newspath.asp?newsid=04398486645354456"
  },
  {
    "publisherId": "edaily",
    "publisherName": "이데일리",
    "specTitle": "기업",
    "categories": [
      "industry"
    ],
    "specUrl": "http://rss.edaily.co.kr/enterprise_news.xml",
    "title": "BMW 재단, 대학생 공모전 '영 이노베이터 드림 프로젝트' 개최",
    "partialText": "BMW 코리아 미래재단이 지난해에 이어 올해도 대학생 대상 사회공헌 아이디어 공모전 ‘영 이노베이터 드림 프로젝트’를 개최한다고 26일 밝혔다. ‘영 이노베이터 드림 프로젝트(Young Innovator Dream Project)’는 대학생들이 지속 가능한 미래를 이끌어갈 인재로 성장할 수 있도록 지원하기 위해 마련된 공모전이다. 지난해 처음 개최돼 33...",
    "date": "2026-02-26T11:05:39.000Z",
    "url": "http://www.edaily.co.kr/news/newspath.asp?newsid=04365686645354456"
  },
  {
    "publisherId": "edaily",
    "publisherName": "이데일리",
    "specTitle": "기업",
    "categories": [
      "industry"
    ],
    "specUrl": "http://rss.edaily.co.kr/enterprise_news.xml",
    "title": "내년 완전자율주행 상용화…2028년 공공부문 UAM 뜬다",
    "partialText": "이르면 내년에는 사람이 운전하지 않아도 스스로 달리는 자율차를 일상에서 만나볼 수 있게 된다. 2028년에는 하늘을 나는 도심항공교통(UAM) 서비스도 공공부문부터 시작될 예정이다. 국토교통부는 인공지능(AI) 기술을 활용해 향후 5년 간 모빌리티 정책의 이정표를 제시하는 ‘2030 모빌리티 혁신성장 로드맵’을 수립해 26일 발표했다. 이번 로드맵은 지난...",
    "date": "2026-02-26T11:00:02.000Z",
    "url": "http://www.edaily.co.kr/news/newspath.asp?newsid=04326326645354456"
  },
  {
    "publisherId": "edaily",
    "publisherName": "이데일리",
    "specTitle": "기업",
    "categories": [
      "industry"
    ],
    "specUrl": "http://rss.edaily.co.kr/enterprise_news.xml",
    "title": "아모레 '비레디', '오일캡처 올인원 로션' 출시",
    "partialText": "아모레퍼시픽(090430)은 자사 남성 화장품(뷰티) 브랜드 ‘비레디’가 신제품 ‘오일캡처 올인원 로션’을 출시한다고 26일 밝혔다.사진=아모레퍼시픽이번 신제품은 과도한 유분을 억제하고 수분을 채우는 것이 집중했다. 징크 미네랄 성분과 천연 미네랄 성분을 배합했다. 아모레퍼시픽에 따르면 해당 제품은 인체적용시험 결과 사용 직후 유분량이 평균 25% 줄은 ...",
    "date": "2026-02-26T10:58:32.000Z",
    "url": "http://www.edaily.co.kr/news/newspath.asp?newsid=04316486645354456"
  },
  {
    "publisherId": "edaily",
    "publisherName": "이데일리",
    "specTitle": "기업",
    "categories": [
      "industry"
    ],
    "specUrl": "http://rss.edaily.co.kr/enterprise_news.xml",
    "title": "2500원짜리 버거 나왔다…노브랜드 버거 '업계 최저가' 승부",
    "partialText": "신세계푸드의 노브랜드 버거가 업계 최저가 신메뉴로 소비자 외식 가격 부담 낮추기에 나선다. 신세계푸드는 노브랜드 버거 ‘어메이징 불고기’ 신제품을 버거업계 최저가인 2500원에 선보인다고 26일 밝혔다.최근 통계청에 따르면 지난해 소비자 물가 상승률은 2.1%를 기록한 반면, 식료품 및 외식 물가는 3.2% 상승하며 전체 평균을 상회했다. 올해 들어서도 ...",
    "date": "2026-02-26T10:52:38.000Z",
    "url": "http://www.edaily.co.kr/news/newspath.asp?newsid=04293526645354456"
  },
  {
    "publisherId": "edaily",
    "publisherName": "이데일리",
    "specTitle": "기업",
    "categories": [
      "industry"
    ],
    "specUrl": "http://rss.edaily.co.kr/enterprise_news.xml",
    "title": "MINI 폴 스미스 에디션, 韓 첫 공개…\"사전예약 완판·300대 더 들인다\"",
    "partialText": "MINI 코리아가 브랜드 특유의 경쾌한 감성에 영국 패션 브랜드 폴 스미스의 감각적인 디자인을 결합한 ‘디 올-일렉트릭 MINI 쿠퍼 SE 폴 스미스 에디션’을 한국에서 처음으로 공개했다. 실물 차량 공개 한 달 전 사전 예약 판매 시작과 동시에 100대 한정 물량이 완판되며 300대의 추가 판매를 준비하고 있다. MINI 코리아는 26일 오전 서울 용산...",
    "date": "2026-02-26T10:33:15.000Z",
    "url": "http://www.edaily.co.kr/news/newspath.asp?newsid=04162326645354456"
  },
  {
    "publisherId": "edaily",
    "publisherName": "이데일리",
    "specTitle": "기업",
    "categories": [
      "industry"
    ],
    "specUrl": "http://rss.edaily.co.kr/enterprise_news.xml",
    "title": "오비맥주, 광주 북구에 `안심귀가 안내판` 설치한 까닭",
    "partialText": "오비맥주는 광주 북구·광주북부경찰서와 협력해 지역 야간 보행 안전 강화를 위한 친환경 ‘안심귀가 안내판’ 설치 사업을 벌였다고 26일 밝혔다.안심귀가 안내판 설치 사업은 오비맥주 광주공장이 위치한 광주 북구 주민들의 야간 보행 안전을 높이고, 지역사회와의 상생을 도모하기 위해 마련했다. 사업비는 지난해 말 오비맥주가 광주 북구와 사랑의열매를 통해 광주 북...",
    "date": "2026-02-26T10:16:31.000Z",
    "url": "http://www.edaily.co.kr/news/newspath.asp?newsid=04073766645354456"
  },
  {
    "publisherId": "edaily",
    "publisherName": "이데일리",
    "specTitle": "기업",
    "categories": [
      "industry"
    ],
    "specUrl": "http://rss.edaily.co.kr/enterprise_news.xml",
    "title": "롯데웰푸드, 출시 37주년 ‘카스타드 꾸미기’ 이벤트 전개",
    "partialText": "롯데웰푸드가 장수 제품인 ‘오리지널 카스타드’ 출시 37주년을 기념해 소비자 참여형 캠페인인 ‘카스타드로 행복을 그려봐’를 진행한다고 26일 밝혔다. 이번 행사는 1989년 출시 이후 카스타드가 고수해온 핵심 가치인 ‘행복’을 소비자들이 직접 시각화해 공유하는 놀이 문화의 일환으로 기획됐다.참여 방법은 간단하다. 제품 포장지에 인쇄된 카스타드 이미지 위에...",
    "date": "2026-02-26T10:10:29.000Z",
    "url": "http://www.edaily.co.kr/news/newspath.asp?newsid=04031126645354456"
  },
  {
    "publisherId": "edaily",
    "publisherName": "이데일리",
    "specTitle": "기업",
    "categories": [
      "industry"
    ],
    "specUrl": "http://rss.edaily.co.kr/enterprise_news.xml",
    "title": "도미노피자, 세이브더칠드런 아동 초청 ‘피자교실’ 개최",
    "partialText": "도미노피자가 아동 권리 보장 및 복지 증진을 위해 세이브더칠드런과 손을 잡았다. 도미노피자는 지난 25일 서울 강남구 도미노피자 본사에서 세이브더칠드런 산하 일원 다함께키움센터 아동들을 초청해 ‘다 함께 피자교실’을 진행했다고 26일 밝혔다. 이번 행사는 아동들에게 직업 체험의 기회를 제공하고 창의적 활동을 통해 정서적 유대감을 형성하기 위해 마련됐다. ...",
    "date": "2026-02-26T10:08:22.000Z",
    "url": "http://www.edaily.co.kr/news/newspath.asp?newsid=04018006645354456"
  },
  {
    "publisherId": "edaily",
    "publisherName": "이데일리",
    "specTitle": "기업",
    "categories": [
      "industry"
    ],
    "specUrl": "http://rss.edaily.co.kr/enterprise_news.xml",
    "title": "겨울철 헌혈 감소에…빙그레 임직원 `사랑의 헌혈` 캠페인",
    "partialText": "빙그레는 설 연휴 이후 혈액 수급이 어려운 시기를 고려해 임직원 대상 ‘사랑의 헌혈 캠페인’을 진행했다고 26일 밝혔다.빙그레는 지난 25일 서울 종로구에 위치한 본사 인근에서 대한적십자사와 협력해 마련했다. 학교 방학과 독감 유행 등으로 헌혈 참여가 감소하는 겨울철 혈액 수급 안정화에 기여하기 위함이다. 이날 캠페인에는 빙그레 임직원 50여명이 자발적으...",
    "date": "2026-02-26T10:06:01.000Z",
    "url": "http://www.edaily.co.kr/news/newspath.asp?newsid=03995046645354456"
  },
  {
    "publisherId": "edaily",
    "publisherName": "이데일리",
    "specTitle": "기업",
    "categories": [
      "industry"
    ],
    "specUrl": "http://rss.edaily.co.kr/enterprise_news.xml",
    "title": "크록스, 새로운 디자인 '리플' 국내 출시",
    "partialText": "크록스는 신발업계 유명 디자이너 스티븐 스미스 합류 이후 첫 결과물인 ‘리플’을 다음달 6일 국내 출시한다고 26일 밝혔다.사진=크록스스미스는 2024년 크록스의 크리에이티브 이노베이션 총괄로 영입돼 디자인을 강화해 왔다. 리플은 크록스가 지향하는 디자인을 집약적으로 보여준다. 리플은 크록스 특유의 디자인과 더불어 기능성과 스타일을 결합했다. 스니커즈 같...",
    "date": "2026-02-26T09:58:52.000Z",
    "url": "http://www.edaily.co.kr/news/newspath.asp?newsid=03913046645354456"
  },
  {
    "publisherId": "edaily",
    "publisherName": "이데일리",
    "specTitle": "기업",
    "categories": [
      "industry"
    ],
    "specUrl": "http://rss.edaily.co.kr/enterprise_news.xml",
    "title": "벤츠 코리아, 4월부터 전국 단일 가격 판매제 시행",
    "partialText": "메르세데스-벤츠 코리아가 전국 단일 가격 판매 체계를 도입한다.메르세데스-벤츠 코리아와 11개 딜러사 관계자들이 지난 25일 서울 신라호텔에서 리테일 오브 더 퓨처 협약식을 하고 있다. (사진=메르세데스-벤츠 코리아)벤츠 코리아는 지난 25일 서울 신라호텔에서 전국 11개 공식 딜러사와 함께 새로운 차량 판매 방식 ‘리테일 오브 더 퓨처(Retail of...",
    "date": "2026-02-26T09:48:11.000Z",
    "url": "http://www.edaily.co.kr/news/newspath.asp?newsid=03808086645354456"
  },
  {
    "publisherId": "edaily",
    "publisherName": "이데일리",
    "specTitle": "기업",
    "categories": [
      "industry"
    ],
    "specUrl": "http://rss.edaily.co.kr/enterprise_news.xml",
    "title": "'21만전자' 돈복 터진다…이재용 주식재산 '40조' 돌파 목전",
    "partialText": "이재용 삼성전자 회장의 주식재산이 40조원 돌파를 목전에 뒀다.젠슨 황 엔비디아 최고경영자와 이재용 삼성전자 회장이 30일 서울 코엑스에서 열린 엔비디아의 그래픽카드(GPU) 지포스 출시 25주년 행사에 참석해 있다 (사진=이데일리 김태형 기자)기업분석전문 한국CXO연구소는 이재용 회장의 주식평가액(2월 25일 기준)이 38조7738억원으로 평가됐다고 2...",
    "date": "2026-02-26T09:46:32.000Z",
    "url": "http://www.edaily.co.kr/news/newspath.asp?newsid=03791686645354456"
  },
  {
    "publisherId": "edaily",
    "publisherName": "이데일리",
    "specTitle": "기업",
    "categories": [
      "industry"
    ],
    "specUrl": "http://rss.edaily.co.kr/enterprise_news.xml",
    "title": "파리바게뜨, 싱가포르 전 매장 `MUIS 공식 할랄 인증` 획득",
    "partialText": "파리바게뜨는 싱가포르 전 매장에 MUIS(싱가포르 이슬람종교위원회) 공식 할랄 인증을 획득해 글로벌 할랄 시장 공략에 속도를 낸다고 26일 밝혔다.이번 인증으로 파리바게뜨는 싱가포르에서 생산부터 매장 내 조리·판매에 이르는 전 과정을 아우르는 할랄 운영 체계를 구축했다. 지난해 준공한 말레이시아 조호르 생산센터에 이어 매장 운영 단계까지 인증 기준을 충족...",
    "date": "2026-02-26T09:45:25.000Z",
    "url": "http://www.edaily.co.kr/news/newspath.asp?newsid=03765446645354456"
  },
  {
    "publisherId": "edaily",
    "publisherName": "이데일리",
    "specTitle": "기업",
    "categories": [
      "industry"
    ],
    "specUrl": "http://rss.edaily.co.kr/enterprise_news.xml",
    "title": "광동제약, 이승재 생산본부장 선임…품질 경쟁력 강화",
    "partialText": "광동제약은 이승재 상무이사(사진)를 신임 생산본부장으로 선임한다고 26일 밝혔다. 이번 인사는 검증된 내부 인재를 통해 조직의 안정성을 도모하고, 생산 공정 전반에 걸친 업무 연속성을 확보하기 위한 조치라고 광동제약은 설명했다.이승재 신임 생산본부장은 품질 최우선 원칙 아래 생산관리 시스템을 고도화하고, 전 제품군의 안정적인 공급 체계를 구축하는 데 역량...",
    "date": "2026-02-26T09:41:02.000Z",
    "url": "http://www.edaily.co.kr/news/newspath.asp?newsid=03716246645354456"
  },
  {
    "publisherId": "edaily",
    "publisherName": "이데일리",
    "specTitle": "기업",
    "categories": [
      "industry"
    ],
    "specUrl": "http://rss.edaily.co.kr/enterprise_news.xml",
    "title": "KGMC, 국내 최초 7m급 저상 전기버스 ‘이-스타나’ 1호차 인도",
    "partialText": "KGM커머셜(KGMC·옛 에디슨모터스)이 국내 최초로 개발한 7m급 저상 전기버스 ‘E-STANA(이-스타나)’ 1호차 인도식을 갖고 본격적인 출고를 시작 했다고 26일 밝혔다.김종현 KGMC 대표이사(왼쪽), 장관수 자경마을버스 대표이사 (사진=KGMC)KGMC는 지난 25일 경기도 광명시에 위치한 자경마을버스에서 김종현 KGMC 대표이사 및 장관수 자...",
    "date": "2026-02-26T09:27:10.000Z",
    "url": "http://www.edaily.co.kr/news/newspath.asp?newsid=03601446645354456"
  },
  {
    "publisherId": "edaily",
    "publisherName": "이데일리",
    "specTitle": "기업",
    "categories": [
      "industry"
    ],
    "specUrl": "http://rss.edaily.co.kr/enterprise_news.xml",
    "title": "테슬라 가격 인하 여파…중고 전기차 시세 '줄하락'",
    "partialText": "테슬라가 모델 Y 등 주요 모델의 국내 판매 가격을 수백만원대 인하하면서 중고 전기차 시장에도 여파가 확산되고 있다. 신차 가격이 내려가자 중고차 시세 역시 연쇄적으로 흔들리는 모습이다.(사진=AFP)26일 직영 중고차 플랫폼 기업 케이카에 따르면 국내 중고차 시장에서 유통 중인 출시 10년 이내 740여개 모델의 평균 시세를 분석한 결과 주요 전기차 가...",
    "date": "2026-02-26T09:26:29.000Z",
    "url": "http://www.edaily.co.kr/news/newspath.asp?newsid=03608006645354456"
  },
  {
    "publisherId": "edaily",
    "publisherName": "이데일리",
    "specTitle": "기업",
    "categories": [
      "industry"
    ],
    "specUrl": "http://rss.edaily.co.kr/enterprise_news.xml",
    "title": "빨간맛 통했다…bhc `스윗칠리킹` 3개월만에 100만 마리 판매",
    "partialText": "다이닝브랜즈그룹의 치킨 브랜드 bhc의 신메뉴 ‘스윗칠리킹’이 누적 판매량 100만 마리를 돌파했다고 26일 밝혔다. 지난해 11월 출시 이후 3개월 만이다.bhc에 따르면 ‘스윗칠리킹’은 지난해 11월 18일 출시한 지 약 한 달 만에 40만 마라에 이어 두 달 만에 80만 마리 판매를 기록했다. 3개월 차에 접어든 현재까지도 판매량의 꺾임 없이 꾸준한...",
    "date": "2026-02-26T09:21:54.000Z",
    "url": "http://www.edaily.co.kr/news/newspath.asp?newsid=03552246645354456"
  }
]