[
  {
    "publisherId": "hankyung",
    "publisherName": "한국경제",
    "specTitle": "정치",
    "categories": [
      "politics"
    ],
    "specUrl": "https://www.hankyung.com/feed/politics",
    "title": "법원장들, 사법개혁 반발 \"숙의 없어…부작용 심각\"",
    "partialText": "",
    "date": "2026-02-25T22:49:49.000Z",
    "url": "https://www.hankyung.com/article/2026022552781"
  },
  {
    "publisherId": "hankyung",
    "publisherName": "한국경제",
    "specTitle": "정치",
    "categories": [
      "politics"
    ],
    "specUrl": "https://www.hankyung.com/feed/politics",
    "title": "공군 F-16C 전투기 추락, 조종사 비상탈출…직접 119 신고",
    "partialText": "",
    "date": "2026-02-25T22:48:31.000Z",
    "url": "https://www.hankyung.com/article/2026022552761"
  },
  {
    "publisherId": "hankyung",
    "publisherName": "한국경제",
    "specTitle": "정치",
    "categories": [
      "politics"
    ],
    "specUrl": "https://www.hankyung.com/feed/politics",
    "title": "주호영 \"통화로 추미애 답변 받았다…회기 내 TK통합 처리 가능\"",
    "partialText": "",
    "date": "2026-02-25T20:58:52.000Z",
    "url": "https://www.hankyung.com/article/202602255191i"
  },
  {
    "publisherId": "hankyung",
    "publisherName": "한국경제",
    "specTitle": "정치",
    "categories": [
      "politics"
    ],
    "specUrl": "https://www.hankyung.com/feed/politics",
    "title": "다음은 '주가 누르기 방지법'…與, 입법 속도낸다",
    "partialText": "",
    "date": "2026-02-25T17:58:02.000Z",
    "url": "https://www.hankyung.com/article/2026022549031"
  },
  {
    "publisherId": "hankyung",
    "publisherName": "한국경제",
    "specTitle": "정치",
    "categories": [
      "politics"
    ],
    "specUrl": "https://www.hankyung.com/feed/politics",
    "title": "李대통령 \"상속·고령자 농지, 강제 매각대상 아니다\"",
    "partialText": "",
    "date": "2026-02-25T17:45:13.000Z",
    "url": "https://www.hankyung.com/article/2026022549091"
  },
  {
    "publisherId": "hankyung",
    "publisherName": "한국경제",
    "specTitle": "정치",
    "categories": [
      "politics"
    ],
    "specUrl": "https://www.hankyung.com/feed/politics",
    "title": "비자발적 취득 자사주도 소각 대상…\"올해만 최대 60兆 될 듯\"",
    "partialText": "",
    "date": "2026-02-25T17:45:08.000Z",
    "url": "https://www.hankyung.com/article/2026022549021"
  },
  {
    "publisherId": "hankyung",
    "publisherName": "한국경제",
    "specTitle": "정치",
    "categories": [
      "politics"
    ],
    "specUrl": "https://www.hankyung.com/feed/politics",
    "title": "[포토] 5·18정신 헌법수록 촉구",
    "partialText": "",
    "date": "2026-02-25T17:44:50.000Z",
    "url": "https://www.hankyung.com/article/2026022549121"
  },
  {
    "publisherId": "hankyung",
    "publisherName": "한국경제",
    "specTitle": "정치",
    "categories": [
      "politics"
    ],
    "specUrl": "https://www.hankyung.com/feed/politics",
    "title": "\"부자노인 기초연금 줄이자\"…당정, 차등지급 추진",
    "partialText": "",
    "date": "2026-02-25T17:43:01.000Z",
    "url": "https://www.hankyung.com/article/2026022549141"
  },
  {
    "publisherId": "hankyung",
    "publisherName": "한국경제",
    "specTitle": "정치",
    "categories": [
      "politics"
    ],
    "specUrl": "https://www.hankyung.com/feed/politics",
    "title": "국힘 중진의원 14명, 26일 장동혁 만난다",
    "partialText": "",
    "date": "2026-02-25T17:41:04.000Z",
    "url": "https://www.hankyung.com/article/2026022549131"
  },
  {
    "publisherId": "hankyung",
    "publisherName": "한국경제",
    "specTitle": "정치",
    "categories": [
      "politics"
    ],
    "specUrl": "https://www.hankyung.com/feed/politics",
    "title": "내달 9일부터 한미 FS연습…\"기동훈련 아직 협의 중\"",
    "partialText": "",
    "date": "2026-02-25T17:40:33.000Z",
    "url": "https://www.hankyung.com/article/2026022549111"
  },
  {
    "publisherId": "hankyung",
    "publisherName": "한국경제",
    "specTitle": "정치",
    "categories": [
      "politics"
    ],
    "specUrl": "https://www.hankyung.com/feed/politics",
    "title": "윤상현 의원 \"서해 전투기 소통 혼선…한미 공조 약화 우려\"",
    "partialText": "",
    "date": "2026-02-25T17:29:19.000Z",
    "url": "https://www.hankyung.com/article/202602254516i"
  },
  {
    "publisherId": "hankyung",
    "publisherName": "한국경제",
    "specTitle": "정치",
    "categories": [
      "politics"
    ],
    "specUrl": "https://www.hankyung.com/feed/politics",
    "title": "여권 재발급 서둘러야…3월부터 20년 만에 수수료 오른다",
    "partialText": "",
    "date": "2026-02-25T16:59:06.000Z",
    "url": "https://www.hankyung.com/article/2026022544397"
  },
  {
    "publisherId": "hankyung",
    "publisherName": "한국경제",
    "specTitle": "정치",
    "categories": [
      "politics"
    ],
    "specUrl": "https://www.hankyung.com/feed/politics",
    "title": "[속보] '법왜곡죄 신설·간첩죄 확대' 형법개정안 본회의 상정…국힘 필버",
    "partialText": "",
    "date": "2026-02-25T16:41:59.000Z",
    "url": "https://www.hankyung.com/article/2026022546107"
  },
  {
    "publisherId": "hankyung",
    "publisherName": "한국경제",
    "specTitle": "정치",
    "categories": [
      "politics"
    ],
    "specUrl": "https://www.hankyung.com/feed/politics",
    "title": "[속보] '자사주 소각 의무화' 상법 개정안, 與주도 국회 본회의 통과",
    "partialText": "",
    "date": "2026-02-25T16:41:40.000Z",
    "url": "https://www.hankyung.com/article/2026022546067"
  },
  {
    "publisherId": "hankyung",
    "publisherName": "한국경제",
    "specTitle": "정치",
    "categories": [
      "politics"
    ],
    "specUrl": "https://www.hankyung.com/feed/politics",
    "title": "김상욱, 울산시장 출마 선언…\"김두겸 비전, 나치·트럼프 연상\"",
    "partialText": "",
    "date": "2026-02-25T16:27:35.000Z",
    "url": "https://www.hankyung.com/article/2026022545197"
  },
  {
    "publisherId": "hankyung",
    "publisherName": "한국경제",
    "specTitle": "정치",
    "categories": [
      "politics"
    ],
    "specUrl": "https://www.hankyung.com/feed/politics",
    "title": "[속보] 李대통령 \"부동산에 묶여있던 돈이 자본시장으로…고무적 현상\"",
    "partialText": "",
    "date": "2026-02-25T16:10:36.000Z",
    "url": "https://www.hankyung.com/article/2026022544907"
  },
  {
    "publisherId": "hankyung",
    "publisherName": "한국경제",
    "specTitle": "정치",
    "categories": [
      "politics"
    ],
    "specUrl": "https://www.hankyung.com/feed/politics",
    "title": "[속보] 與, 법왜곡죄 막판 수정…\"위헌소지 최소화해 처리\"",
    "partialText": "",
    "date": "2026-02-25T16:10:17.000Z",
    "url": "https://www.hankyung.com/article/2026022544887"
  },
  {
    "publisherId": "hankyung",
    "publisherName": "한국경제",
    "specTitle": "정치",
    "categories": [
      "politics"
    ],
    "specUrl": "https://www.hankyung.com/feed/politics",
    "title": "감사원 \"담합 자진신고 감면제도, 기업들 악용\"…제도개선 요구",
    "partialText": "",
    "date": "2026-02-25T16:04:14.000Z",
    "url": "https://www.hankyung.com/article/202602254257i"
  },
  {
    "publisherId": "hankyung",
    "publisherName": "한국경제",
    "specTitle": "정치",
    "categories": [
      "politics"
    ],
    "specUrl": "https://www.hankyung.com/feed/politics",
    "title": "이부진 \"한국 멋있는 나라 됐다\" 李 \"바가지요금 근절해야\"",
    "partialText": "",
    "date": "2026-02-25T15:43:28.000Z",
    "url": "https://www.hankyung.com/article/2026022543507"
  },
  {
    "publisherId": "hankyung",
    "publisherName": "한국경제",
    "specTitle": "정치",
    "categories": [
      "politics"
    ],
    "specUrl": "https://www.hankyung.com/feed/politics",
    "title": "與윤건영, 공천헌금 범죄 공소시효 선거 후 6개월 → 5년 연장법 발의",
    "partialText": "",
    "date": "2026-02-25T15:34:55.000Z",
    "url": "https://www.hankyung.com/article/202602254278i"
  },
  {
    "publisherId": "hankyung",
    "publisherName": "한국경제",
    "specTitle": "정치",
    "categories": [
      "politics"
    ],
    "specUrl": "https://www.hankyung.com/feed/politics",
    "title": "與검찰 조작기소 특위 위원장 이성윤→한병도…의원 모임은 유지",
    "partialText": "",
    "date": "2026-02-25T14:54:26.000Z",
    "url": "https://www.hankyung.com/article/202602253621i"
  },
  {
    "publisherId": "hankyung",
    "publisherName": "한국경제",
    "specTitle": "정치",
    "categories": [
      "politics"
    ],
    "specUrl": "https://www.hankyung.com/feed/politics",
    "title": "한미 연합 '자유의 방패' 훈련 내달 실시…\"전작권 전환 준비\"",
    "partialText": "",
    "date": "2026-02-25T14:13:29.000Z",
    "url": "https://www.hankyung.com/article/2026022540577"
  },
  {
    "publisherId": "hankyung",
    "publisherName": "한국경제",
    "specTitle": "정치",
    "categories": [
      "politics"
    ],
    "specUrl": "https://www.hankyung.com/feed/politics",
    "title": "국힘 \"정원오, 0·2세 때 논밭 600평 매매\"…鄭 측 \"가짜뉴스\"",
    "partialText": "",
    "date": "2026-02-25T13:53:15.000Z",
    "url": "https://www.hankyung.com/article/2026022539597"
  },
  {
    "publisherId": "hankyung",
    "publisherName": "한국경제",
    "specTitle": "정치",
    "categories": [
      "politics"
    ],
    "specUrl": "https://www.hankyung.com/feed/politics",
    "title": "\"2살에 논 매입한 정원오부터 조사\" vs \"가문 관습따른 것\"",
    "partialText": "",
    "date": "2026-02-25T13:41:33.000Z",
    "url": "https://www.hankyung.com/article/202602253846i"
  },
  {
    "publisherId": "hankyung",
    "publisherName": "한국경제",
    "specTitle": "정치",
    "categories": [
      "politics"
    ],
    "specUrl": "https://www.hankyung.com/feed/politics",
    "title": "용인반도체 산단 두고 친명 내전…강위원 \"한준호 다를 줄 알았다\"",
    "partialText": "",
    "date": "2026-02-25T11:18:58.000Z",
    "url": "https://www.hankyung.com/article/202602241932i"
  },
  {
    "publisherId": "hankyung",
    "publisherName": "한국경제",
    "specTitle": "정치",
    "categories": [
      "politics"
    ],
    "specUrl": "https://www.hankyung.com/feed/politics",
    "title": "\"깔깔대던 우리\"…배현진, 장동혁과 추억 사진 올렸다 삭제",
    "partialText": "",
    "date": "2026-02-25T11:01:27.000Z",
    "url": "https://www.hankyung.com/article/2026022533557"
  },
  {
    "publisherId": "hankyung",
    "publisherName": "한국경제",
    "specTitle": "정치",
    "categories": [
      "politics"
    ],
    "specUrl": "https://www.hankyung.com/feed/politics",
    "title": "[속보] 이학재 인천공항공사 사장 \"지방선거 출마할 생각 없어\"",
    "partialText": "",
    "date": "2026-02-25T10:20:33.000Z",
    "url": "https://www.hankyung.com/article/2026022534097"
  },
  {
    "publisherId": "hankyung",
    "publisherName": "한국경제",
    "specTitle": "정치",
    "categories": [
      "politics"
    ],
    "specUrl": "https://www.hankyung.com/feed/politics",
    "title": "李대통령 \"관리비 바가지는 범죄\"…서울시장 후보들 반응",
    "partialText": "",
    "date": "2026-02-25T10:01:50.000Z",
    "url": "https://www.hankyung.com/article/2026022531417"
  },
  {
    "publisherId": "hankyung",
    "publisherName": "한국경제",
    "specTitle": "정치",
    "categories": [
      "politics"
    ],
    "specUrl": "https://www.hankyung.com/feed/politics",
    "title": "李 대통령 \"상속받은 농지는 매각 명령대상 아니다\"",
    "partialText": "",
    "date": "2026-02-25T09:20:56.000Z",
    "url": "https://www.hankyung.com/article/202602253075i"
  },
  {
    "publisherId": "hankyung",
    "publisherName": "한국경제",
    "specTitle": "정치",
    "categories": [
      "politics"
    ],
    "specUrl": "https://www.hankyung.com/feed/politics",
    "title": "'서해 훈련' 주한미군 \"대비 태세엔 사과 안해\"…국방부에 반박",
    "partialText": "",
    "date": "2026-02-25T09:01:36.000Z",
    "url": "https://www.hankyung.com/article/202602252908i"
  },
  {
    "publisherId": "hankyung",
    "publisherName": "한국경제",
    "specTitle": "정치",
    "categories": [
      "politics"
    ],
    "specUrl": "https://www.hankyung.com/feed/politics",
    "title": "李 \"농지매각 명령에 공산당 운운…경자유전 원칙 헌법에 명시\"",
    "partialText": "",
    "date": "2026-02-25T08:55:42.000Z",
    "url": "https://www.hankyung.com/article/2026022529177"
  },
  {
    "publisherId": "hankyung",
    "publisherName": "한국경제",
    "specTitle": "정치",
    "categories": [
      "politics"
    ],
    "specUrl": "https://www.hankyung.com/feed/politics",
    "title": "'100원 생리대' 출시 소식에…李대통령 \"깨끗한나라에 감사\"",
    "partialText": "",
    "date": "2026-02-25T08:24:10.000Z",
    "url": "https://www.hankyung.com/article/2026022528127"
  },
  {
    "publisherId": "hankyung",
    "publisherName": "한국경제",
    "specTitle": "정치",
    "categories": [
      "politics"
    ],
    "specUrl": "https://www.hankyung.com/feed/politics",
    "title": "李 대통령 \"민주당 잘 하고 있다…대통령 뒷전 된 일 없어\"",
    "partialText": "",
    "date": "2026-02-25T07:57:01.000Z",
    "url": "https://www.hankyung.com/article/2026022526847"
  },
  {
    "publisherId": "hankyung",
    "publisherName": "한국경제",
    "specTitle": "정치",
    "categories": [
      "politics"
    ],
    "specUrl": "https://www.hankyung.com/feed/politics",
    "title": "李대통령, 오늘 정세균·김진표 만난다…與상임고문단과 오찬",
    "partialText": "",
    "date": "2026-02-25T07:18:42.000Z",
    "url": "https://www.hankyung.com/article/2026022526347"
  },
  {
    "publisherId": "hankyung",
    "publisherName": "한국경제",
    "specTitle": "정치",
    "categories": [
      "politics"
    ],
    "specUrl": "https://www.hankyung.com/feed/politics",
    "title": "李 대통령 \"자사주 소각 입법 한시라도 빨리 돼야\"",
    "partialText": "",
    "date": "2026-02-25T07:12:08.000Z",
    "url": "https://www.hankyung.com/article/202602252630i"
  },
  {
    "publisherId": "hankyung",
    "publisherName": "한국경제",
    "specTitle": "정치",
    "categories": [
      "politics"
    ],
    "specUrl": "https://www.hankyung.com/feed/politics",
    "title": "미, 슈퍼 301조 韓조사 가능성에…강경화 \"국익 부합하게 대응\"",
    "partialText": "",
    "date": "2026-02-25T06:49:41.000Z",
    "url": "https://www.hankyung.com/article/2026022525947"
  },
  {
    "publisherId": "hankyung",
    "publisherName": "한국경제",
    "specTitle": "정치",
    "categories": [
      "politics"
    ],
    "specUrl": "https://www.hankyung.com/feed/politics",
    "title": "민주당 계양을 신경전…김남준 \"출마\" 송영길 \"당 결정 따른다\"",
    "partialText": "",
    "date": "2026-02-24T18:19:01.000Z",
    "url": "https://www.hankyung.com/article/2026022417887"
  },
  {
    "publisherId": "hankyung",
    "publisherName": "한국경제",
    "specTitle": "정치",
    "categories": [
      "politics"
    ],
    "specUrl": "https://www.hankyung.com/feed/politics",
    "title": "체포안 가결 전 떠난 강선우…\"국민에게 할 말\" 질문에 묵묵부답",
    "partialText": "",
    "date": "2026-02-24T18:08:43.000Z",
    "url": "https://www.hankyung.com/article/2026022421567"
  },
  {
    "publisherId": "hankyung",
    "publisherName": "한국경제",
    "specTitle": "정치",
    "categories": [
      "politics"
    ],
    "specUrl": "https://www.hankyung.com/feed/politics",
    "title": "與 \"주총 의장도 주주가 지명한다\"",
    "partialText": "",
    "date": "2026-02-24T17:51:08.000Z",
    "url": "https://www.hankyung.com/article/2026022420911"
  },
  {
    "publisherId": "hankyung",
    "publisherName": "한국경제",
    "specTitle": "정치",
    "categories": [
      "politics"
    ],
    "specUrl": "https://www.hankyung.com/feed/politics",
    "title": "여야, 3차 상법·사법개혁법 '충돌'…39일만에 또 필버 정국",
    "partialText": "",
    "date": "2026-02-24T17:50:57.000Z",
    "url": "https://www.hankyung.com/article/2026022420941"
  },
  {
    "publisherId": "hankyung",
    "publisherName": "한국경제",
    "specTitle": "정치",
    "categories": [
      "politics"
    ],
    "specUrl": "https://www.hankyung.com/feed/politics",
    "title": "전남광주통합법 법사위 통과…충남대전·대구경북은 '보류'",
    "partialText": "",
    "date": "2026-02-24T17:50:04.000Z",
    "url": "https://www.hankyung.com/article/2026022420961"
  },
  {
    "publisherId": "hankyung",
    "publisherName": "한국경제",
    "specTitle": "정치",
    "categories": [
      "politics"
    ],
    "specUrl": "https://www.hankyung.com/feed/politics",
    "title": "北김여정, 장관급 '당 부장'으로 승진",
    "partialText": "",
    "date": "2026-02-24T17:49:39.000Z",
    "url": "https://www.hankyung.com/article/2026022420951"
  },
  {
    "publisherId": "hankyung",
    "publisherName": "한국경제",
    "specTitle": "정치",
    "categories": [
      "politics"
    ],
    "specUrl": "https://www.hankyung.com/feed/politics",
    "title": "\"방산·AI 협력 확대\"…강훈식, UAE 출국",
    "partialText": "",
    "date": "2026-02-24T17:48:48.000Z",
    "url": "https://www.hankyung.com/article/2026022420971"
  },
  {
    "publisherId": "hankyung",
    "publisherName": "한국경제",
    "specTitle": "정치",
    "categories": [
      "politics"
    ],
    "specUrl": "https://www.hankyung.com/feed/politics",
    "title": "경자유전 꺼낸 李대통령, 이번엔 '투기용 농지' 정조준…부동산 전선 확대",
    "partialText": "",
    "date": "2026-02-24T17:41:12.000Z",
    "url": "https://www.hankyung.com/article/2026022420711"
  },
  {
    "publisherId": "hankyung",
    "publisherName": "한국경제",
    "specTitle": "정치",
    "categories": [
      "politics"
    ],
    "specUrl": "https://www.hankyung.com/feed/politics",
    "title": "李 대통령 \"모든 문제 원천은 부동산…농지도 강제매각 검토\"",
    "partialText": "",
    "date": "2026-02-24T17:37:18.000Z",
    "url": "https://www.hankyung.com/article/2026022421141"
  },
  {
    "publisherId": "hankyung",
    "publisherName": "한국경제",
    "specTitle": "정치",
    "categories": [
      "politics"
    ],
    "specUrl": "https://www.hankyung.com/feed/politics",
    "title": "與 법안 강행 처리…국힘 \"금주 상임위 전면 보이콧\"",
    "partialText": "",
    "date": "2026-02-24T17:20:55.000Z",
    "url": "https://www.hankyung.com/article/2026022419967"
  },
  {
    "publisherId": "hankyung",
    "publisherName": "한국경제",
    "specTitle": "정치",
    "categories": [
      "politics"
    ],
    "specUrl": "https://www.hankyung.com/feed/politics",
    "title": "외교부 \"美와 적어도 '안보 협의'는 잘돼가는 중\"",
    "partialText": "",
    "date": "2026-02-24T17:06:07.000Z",
    "url": "https://www.hankyung.com/article/202602241722i"
  },
  {
    "publisherId": "hankyung",
    "publisherName": "한국경제",
    "specTitle": "정치",
    "categories": [
      "politics"
    ],
    "specUrl": "https://www.hankyung.com/feed/politics",
    "title": "[속보] 李 대통령 \"충남대전 통합, 일방적으로 강행할 수는 없어\"",
    "partialText": "",
    "date": "2026-02-24T17:00:02.000Z",
    "url": "https://www.hankyung.com/article/2026022418877"
  },
  {
    "publisherId": "hankyung",
    "publisherName": "한국경제",
    "specTitle": "정치",
    "categories": [
      "politics"
    ],
    "specUrl": "https://www.hankyung.com/feed/politics",
    "title": "김여정, 노동당 장관급으로 승진…北, 대외 메시지는 '침묵'",
    "partialText": "",
    "date": "2026-02-24T16:30:20.000Z",
    "url": "https://www.hankyung.com/article/202602241529i"
  },
  {
    "publisherId": "hankyung",
    "publisherName": "한국경제",
    "specTitle": "정치",
    "categories": [
      "politics"
    ],
    "specUrl": "https://www.hankyung.com/feed/politics",
    "title": "[포토] 고성 오고가는 국회 법사위",
    "partialText": "",
    "date": "2026-02-24T16:17:18.000Z",
    "url": "https://www.hankyung.com/article/202602241743i"
  }
]