[
  {
    "publisherId": "sedaily",
    "publisherName": "서울경제",
    "specTitle": "스포츠",
    "categories": [
      "sports"
    ],
    "specUrl": "https://www.sedaily.com/rss/sports",
    "title": "화끈한 대한민국 女골퍼 연속 ‘톱10’ 도전…‘황유민 3연속’ ‘이소미 4연속’ ‘김세영·유해란 5연속’ VS ‘티띠꾼 9연속’",
    "partialText": "",
    "date": "2026-02-25T22:04:27.000Z",
    "url": "https://www.sedaily.com/article/20012765"
  },
  {
    "publisherId": "sedaily",
    "publisherName": "서울경제",
    "specTitle": "스포츠",
    "categories": [
      "sports"
    ],
    "specUrl": "https://www.sedaily.com/rss/sports",
    "title": "올림픽 ‘스노보드 빅에어’ 동메달 유승은, 체전 하프파이프 3위",
    "partialText": "",
    "date": "2026-02-25T20:23:25.000Z",
    "url": "https://www.sedaily.com/article/20012745"
  },
  {
    "publisherId": "sedaily",
    "publisherName": "서울경제",
    "specTitle": "스포츠",
    "categories": [
      "sports"
    ],
    "specUrl": "https://www.sedaily.com/rss/sports",
    "title": "“승격 가장 가까운 팀은 수원…‘탈 2부급 전력’ 이정효호에 쏟아진 ‘집중 견제’",
    "partialText": "",
    "date": "2026-02-25T17:31:47.000Z",
    "url": "https://www.sedaily.com/article/20012646"
  },
  {
    "publisherId": "sedaily",
    "publisherName": "서울경제",
    "specTitle": "스포츠",
    "categories": [
      "sports"
    ],
    "specUrl": "https://www.sedaily.com/rss/sports",
    "title": "임종언·이해인 후원한 중소기업 사장님, 알고보니 3대째 체육단체장",
    "partialText": "",
    "date": "2026-02-25T16:07:27.000Z",
    "url": "https://www.sedaily.com/article/20012575"
  },
  {
    "publisherId": "sedaily",
    "publisherName": "서울경제",
    "specTitle": "스포츠",
    "categories": [
      "sports"
    ],
    "specUrl": "https://www.sedaily.com/rss/sports",
    "title": "“새로운 별 새길 것”·“증명할 것”…첫 시즌 앞둔 신임 감독들의 ‘출사표’ 5인 5색",
    "partialText": "",
    "date": "2026-02-25T15:30:05.000Z",
    "url": "https://www.sedaily.com/article/20012513"
  },
  {
    "publisherId": "sedaily",
    "publisherName": "서울경제",
    "specTitle": "스포츠",
    "categories": [
      "sports"
    ],
    "specUrl": "https://www.sedaily.com/rss/sports",
    "title": "‘주장 완장’ 찬 손흥민 45분 활약…LAFC, 북중미 챔피언스컵 16강 진출",
    "partialText": "",
    "date": "2026-02-25T15:24:04.000Z",
    "url": "https://www.sedaily.com/article/20012547"
  },
  {
    "publisherId": "sedaily",
    "publisherName": "서울경제",
    "specTitle": "스포츠",
    "categories": [
      "sports"
    ],
    "specUrl": "https://www.sedaily.com/rss/sports",
    "title": "올해 한국여자오픈 타이틀스폰서는 메르세데스-벤츠",
    "partialText": "",
    "date": "2026-02-25T14:46:08.000Z",
    "url": "https://www.sedaily.com/article/20012518"
  },
  {
    "publisherId": "sedaily",
    "publisherName": "서울경제",
    "specTitle": "스포츠",
    "categories": [
      "sports"
    ],
    "specUrl": "https://www.sedaily.com/rss/sports",
    "title": "브이씨, 미국 뉴턴 골프 샤프트 수입 판매[필드소식]",
    "partialText": "",
    "date": "2026-02-25T10:13:16.000Z",
    "url": "https://www.sedaily.com/article/20012367"
  },
  {
    "publisherId": "sedaily",
    "publisherName": "서울경제",
    "specTitle": "스포츠",
    "categories": [
      "sports"
    ],
    "specUrl": "https://www.sedaily.com/rss/sports",
    "title": "‘내손안의 LIV 골프’…‘나만의 팀’ 만드는 판타지리그 론칭",
    "partialText": "",
    "date": "2026-02-25T07:40:56.000Z",
    "url": "https://www.sedaily.com/article/20012255"
  },
  {
    "publisherId": "sedaily",
    "publisherName": "서울경제",
    "specTitle": "스포츠",
    "categories": [
      "sports"
    ],
    "specUrl": "https://www.sedaily.com/rss/sports",
    "title": "‘왼손 베테랑’ 세일, 애틀랜타와 연장 계약…1년 2700만 달러 규모",
    "partialText": "",
    "date": "2026-02-25T07:40:05.000Z",
    "url": "https://www.sedaily.com/article/20012254"
  },
  {
    "publisherId": "sedaily",
    "publisherName": "서울경제",
    "specTitle": "스포츠",
    "categories": [
      "sports"
    ],
    "specUrl": "https://www.sedaily.com/rss/sports",
    "title": "진화한 ‘반반볼’ Q-스타 투어 디바이드 컬러팝 출시[필드소식]",
    "partialText": "",
    "date": "2026-02-25T07:08:05.000Z",
    "url": "https://www.sedaily.com/article/20011952"
  },
  {
    "publisherId": "sedaily",
    "publisherName": "서울경제",
    "specTitle": "스포츠",
    "categories": [
      "sports"
    ],
    "specUrl": "https://www.sedaily.com/rss/sports",
    "title": "또 장타자 만난 윤이나, 오스틴 김과 샷 대결…황유민은 ‘LPGA 장타 1위’ 매슈스와 같은 조",
    "partialText": "",
    "date": "2026-02-24T23:23:39.000Z",
    "url": "https://www.sedaily.com/article/20012220"
  },
  {
    "publisherId": "sedaily",
    "publisherName": "서울경제",
    "specTitle": "스포츠",
    "categories": [
      "sports"
    ],
    "specUrl": "https://www.sedaily.com/rss/sports",
    "title": "‘2관왕’ 김길리·‘韓 최다 메달’ 최민정…팀 코리아 ‘금의환향’",
    "partialText": "",
    "date": "2026-02-24T21:05:45.000Z",
    "url": "https://www.sedaily.com/article/20012202"
  },
  {
    "publisherId": "sedaily",
    "publisherName": "서울경제",
    "specTitle": "스포츠",
    "categories": [
      "sports"
    ],
    "specUrl": "https://www.sedaily.com/rss/sports",
    "title": "손흥민 넘어선 이강인, 2025년 KFA ‘올해의 선수’ 등극",
    "partialText": "",
    "date": "2026-02-24T17:27:05.000Z",
    "url": "https://www.sedaily.com/article/20012096"
  },
  {
    "publisherId": "sedaily",
    "publisherName": "서울경제",
    "specTitle": "스포츠",
    "categories": [
      "sports"
    ],
    "specUrl": "https://www.sedaily.com/rss/sports",
    "title": "韓 최고 랭커 김효주, 세계 7위로 ‘껑충’...김세영은 10위",
    "partialText": "",
    "date": "2026-02-24T17:12:27.000Z",
    "url": "https://www.sedaily.com/article/20011780"
  },
  {
    "publisherId": "sedaily",
    "publisherName": "서울경제",
    "specTitle": "스포츠",
    "categories": [
      "sports"
    ],
    "specUrl": "https://www.sedaily.com/rss/sports",
    "title": "‘LPGA 혼다 톱10’이 이끈 ‘진격의 세계 랭킹’…‘김효주 9위→7위’ ‘최혜진 15위→14위’ ‘이소미 38위→35위’",
    "partialText": "",
    "date": "2026-02-24T15:16:43.000Z",
    "url": "https://www.sedaily.com/article/20012009"
  },
  {
    "publisherId": "sedaily",
    "publisherName": "서울경제",
    "specTitle": "스포츠",
    "categories": [
      "sports"
    ],
    "specUrl": "https://www.sedaily.com/rss/sports",
    "title": "‘대기만성형 선수’ 배소현, 비넘버원과 매니지먼트 계약[필드소식]",
    "partialText": "",
    "date": "2026-02-24T14:46:15.000Z",
    "url": "https://www.sedaily.com/article/20011989"
  },
  {
    "publisherId": "sedaily",
    "publisherName": "서울경제",
    "specTitle": "스포츠",
    "categories": [
      "sports"
    ],
    "specUrl": "https://www.sedaily.com/rss/sports",
    "title": "FJ, ‘임성재 골프화’ PRO/SL 차세대 제품 공개[필드소식]",
    "partialText": "",
    "date": "2026-02-24T13:41:27.000Z",
    "url": "https://www.sedaily.com/article/20011938"
  },
  {
    "publisherId": "sedaily",
    "publisherName": "서울경제",
    "specTitle": "스포츠",
    "categories": [
      "sports"
    ],
    "specUrl": "https://www.sedaily.com/rss/sports",
    "title": "‘병가’ 이경훈 11개월 만 PGA 복귀",
    "partialText": "",
    "date": "2026-02-24T12:30:58.000Z",
    "url": "https://www.sedaily.com/article/20011911"
  },
  {
    "publisherId": "sedaily",
    "publisherName": "서울경제",
    "specTitle": "스포츠",
    "categories": [
      "sports"
    ],
    "specUrl": "https://www.sedaily.com/rss/sports",
    "title": "“세련미의 극치”…미즈노, 한정판 ‘MX 포지드 블랙’ 에디션 출시[필드소식]",
    "partialText": "",
    "date": "2026-02-24T12:20:32.000Z",
    "url": "https://www.sedaily.com/article/20011907"
  },
  {
    "publisherId": "sedaily",
    "publisherName": "서울경제",
    "specTitle": "스포츠",
    "categories": [
      "sports"
    ],
    "specUrl": "https://www.sedaily.com/rss/sports",
    "title": "인구 16만 ‘소국’ 퀴라소 월드컵 본선 이끈 아드보카트 감독, 딸 건강 문제로 감독직 사임",
    "partialText": "",
    "date": "2026-02-24T09:03:48.000Z",
    "url": "https://www.sedaily.com/article/20011764"
  },
  {
    "publisherId": "sedaily",
    "publisherName": "서울경제",
    "specTitle": "스포츠",
    "categories": [
      "sports"
    ],
    "specUrl": "https://www.sedaily.com/rss/sports",
    "title": "“스타일은 완벽한 기능성으로부터”...챌린저, 2026 SS 컬렉션 공개[필드소식]",
    "partialText": "",
    "date": "2026-02-24T07:53:44.000Z",
    "url": "https://www.sedaily.com/article/20011732"
  },
  {
    "publisherId": "sedaily",
    "publisherName": "서울경제",
    "specTitle": "스포츠",
    "categories": [
      "sports"
    ],
    "specUrl": "https://www.sedaily.com/rss/sports",
    "title": "이해인, 보그 이탈리아 선정 ‘올림픽 룩스’ 2위에[밀라노 코르티나 2026]",
    "partialText": "",
    "date": "2026-02-24T07:47:05.000Z",
    "url": "https://www.sedaily.com/article/20011585"
  },
  {
    "publisherId": "sedaily",
    "publisherName": "서울경제",
    "specTitle": "스포츠",
    "categories": [
      "sports"
    ],
    "specUrl": "https://www.sedaily.com/rss/sports",
    "title": "비니시우스에 ‘인종 차별 의혹’ 프레스티아니, 1경기 출전 정지 임시 처분",
    "partialText": "",
    "date": "2026-02-24T07:36:50.000Z",
    "url": "https://www.sedaily.com/article/20011730"
  },
  {
    "publisherId": "sedaily",
    "publisherName": "서울경제",
    "specTitle": "스포츠",
    "categories": [
      "sports"
    ],
    "specUrl": "https://www.sedaily.com/rss/sports",
    "title": "“무심코 볼 놓으면 2벌타”…볼 닦기와 프리퍼드 라이 헷갈린 신다인[골프 규칙]",
    "partialText": "",
    "date": "2026-02-24T05:00:05.000Z",
    "url": "https://www.sedaily.com/article/20011657"
  },
  {
    "publisherId": "sedaily",
    "publisherName": "서울경제",
    "specTitle": "스포츠",
    "categories": [
      "sports"
    ],
    "specUrl": "https://www.sedaily.com/rss/sports",
    "title": "‘10년 7승’ 한국 女골퍼 가장 ‘우승 확률’ 높은 LPGA 대회…부활 노리는 고진영, 첫 출전 우승 꿈꾸는 황유민과 윤이나",
    "partialText": "",
    "date": "2026-02-23T20:10:08.000Z",
    "url": "https://www.sedaily.com/article/20011672"
  },
  {
    "publisherId": "sedaily",
    "publisherName": "서울경제",
    "specTitle": "스포츠",
    "categories": [
      "sports"
    ],
    "specUrl": "https://www.sedaily.com/rss/sports",
    "title": "대만 전지훈련 중 도박장 출입한 롯데 4명, 50경기·30경기 출장정지 중징계",
    "partialText": "",
    "date": "2026-02-23T18:31:18.000Z",
    "url": "https://www.sedaily.com/article/20011653"
  },
  {
    "publisherId": "sedaily",
    "publisherName": "서울경제",
    "specTitle": "스포츠",
    "categories": [
      "sports"
    ],
    "specUrl": "https://www.sedaily.com/rss/sports",
    "title": "골프황제 앞에서…브리지먼 ‘100년 무대’ 정상 올랐다",
    "partialText": "",
    "date": "2026-02-23T17:29:40.000Z",
    "url": "https://www.sedaily.com/article/20011568"
  },
  {
    "publisherId": "sedaily",
    "publisherName": "서울경제",
    "specTitle": "스포츠",
    "categories": [
      "sports"
    ],
    "specUrl": "https://www.sedaily.com/rss/sports",
    "title": "트리플 보기에 발목 잡힌 김주형, 김시우와 나란히 공동 34위",
    "partialText": "",
    "date": "2026-02-23T17:29:19.000Z",
    "url": "https://www.sedaily.com/article/20011567"
  },
  {
    "publisherId": "sedaily",
    "publisherName": "서울경제",
    "specTitle": "스포츠",
    "categories": [
      "sports"
    ],
    "specUrl": "https://www.sedaily.com/rss/sports",
    "title": "클로이 김 父 “최가온, 엄청난 집념의 선수…눈부신 기량 오래 유지하길”[밀라노 코르티나 2026]",
    "partialText": "",
    "date": "2026-02-23T17:28:54.000Z",
    "url": "https://www.sedaily.com/article/20011565"
  },
  {
    "publisherId": "sedaily",
    "publisherName": "서울경제",
    "specTitle": "스포츠",
    "categories": [
      "sports"
    ],
    "specUrl": "https://www.sedaily.com/rss/sports",
    "title": "기적의 ‘역전 金’ 최가온, 美 방송사 선정 ‘동계올림픽서 떠오른 스타 13인’[밀라노 코르티나 2026]",
    "partialText": "",
    "date": "2026-02-23T17:28:03.000Z",
    "url": "https://www.sedaily.com/article/20011564"
  },
  {
    "publisherId": "sedaily",
    "publisherName": "서울경제",
    "specTitle": "스포츠",
    "categories": [
      "sports"
    ],
    "specUrl": "https://www.sedaily.com/rss/sports",
    "title": "오현규 3연속골·조규성 또 부상…대표팀 원톱 라이벌 ‘희비’",
    "partialText": "",
    "date": "2026-02-23T17:27:41.000Z",
    "url": "https://www.sedaily.com/article/20011563"
  },
  {
    "publisherId": "sedaily",
    "publisherName": "서울경제",
    "specTitle": "스포츠",
    "categories": [
      "sports"
    ],
    "specUrl": "https://www.sedaily.com/rss/sports",
    "title": "심판 운영 불신 해소 위해 ‘칼’ 빼든 축구협회…투명성·공정성 제고 위한 심판 정책 발표",
    "partialText": "",
    "date": "2026-02-23T16:30:27.000Z",
    "url": "https://www.sedaily.com/article/20011536"
  },
  {
    "publisherId": "sedaily",
    "publisherName": "서울경제",
    "specTitle": "스포츠",
    "categories": [
      "sports"
    ],
    "specUrl": "https://www.sedaily.com/rss/sports",
    "title": "한국프로축구연맹·쿠팡플레이, 포괄적 파트너십 5년 연장…“K리그 양적·질적 성장 위해 협력할 것”",
    "partialText": "",
    "date": "2026-02-23T14:37:24.000Z",
    "url": "https://www.sedaily.com/article/20011472"
  },
  {
    "publisherId": "sedaily",
    "publisherName": "서울경제",
    "specTitle": "스포츠",
    "categories": [
      "sports"
    ],
    "specUrl": "https://www.sedaily.com/rss/sports",
    "title": "LPGA 생애 상금 ‘진격의 K골퍼들’…‘김세영 11위→10위’ ‘최혜진 71위→70위’ 유해란 79위, 이미향 83위, 이소미 199위 상승",
    "partialText": "",
    "date": "2026-02-23T13:14:21.000Z",
    "url": "https://www.sedaily.com/article/20011431"
  },
  {
    "publisherId": "sedaily",
    "publisherName": "서울경제",
    "specTitle": "스포츠",
    "categories": [
      "sports"
    ],
    "specUrl": "https://www.sedaily.com/rss/sports",
    "title": "‘간판 타자’ 노시환, 한화와 비FA 다년 계약 체결…11년 307억 ‘역대 최장·최대 계약’",
    "partialText": "",
    "date": "2026-02-23T10:13:15.000Z",
    "url": "https://www.sedaily.com/article/20011323"
  },
  {
    "publisherId": "sedaily",
    "publisherName": "서울경제",
    "specTitle": "스포츠",
    "categories": [
      "sports"
    ],
    "specUrl": "https://www.sedaily.com/rss/sports",
    "title": "‘딱 1타 부족’ 셰플러, 톱10 행진 ‘18’에서 마감…톱4 연속 입상도 8회에서 스톱",
    "partialText": "",
    "date": "2026-02-23T08:37:18.000Z",
    "url": "https://www.sedaily.com/article/20011229"
  },
  {
    "publisherId": "sedaily",
    "publisherName": "서울경제",
    "specTitle": "스포츠",
    "categories": [
      "sports"
    ],
    "specUrl": "https://www.sedaily.com/rss/sports",
    "title": "미국, 캐나다 꺾고 46년 만에 아이스하키 금메달[밀라노 코르티나 2026]",
    "partialText": "",
    "date": "2026-02-23T07:54:15.000Z",
    "url": "https://www.sedaily.com/article/20011212"
  },
  {
    "publisherId": "sedaily",
    "publisherName": "서울경제",
    "specTitle": "스포츠",
    "categories": [
      "sports"
    ],
    "specUrl": "https://www.sedaily.com/rss/sports",
    "title": "마스터바니에디션, 산뜻한 컬러의 봄 필드 커플 스타일링 공개[필드소식]",
    "partialText": "",
    "date": "2026-02-23T07:49:11.000Z",
    "url": "https://www.sedaily.com/article/20011210"
  },
  {
    "publisherId": "sedaily",
    "publisherName": "서울경제",
    "specTitle": "스포츠",
    "categories": [
      "sports"
    ],
    "specUrl": "https://www.sedaily.com/rss/sports",
    "title": "“4년 후 알프스서 다시 만나요”…성대하게 막 내린 17일간의 열전[밀라노 코르티나 2026]",
    "partialText": "",
    "date": "2026-02-23T07:14:16.000Z",
    "url": "https://www.sedaily.com/article/20011201"
  },
  {
    "publisherId": "sedaily",
    "publisherName": "서울경제",
    "specTitle": "스포츠",
    "categories": [
      "sports"
    ],
    "specUrl": "https://www.sedaily.com/rss/sports",
    "title": "2연속 ‘톱10’ 휩쓴 대한민국 女골퍼들…‘개막전 5명’ 이어 ‘혼다 타일랜드 6명’ 톱10 행진",
    "partialText": "",
    "date": "2026-02-22T21:28:53.000Z",
    "url": "https://www.sedaily.com/article/20011170"
  },
  {
    "publisherId": "sedaily",
    "publisherName": "서울경제",
    "specTitle": "스포츠",
    "categories": [
      "sports"
    ],
    "specUrl": "https://www.sedaily.com/rss/sports",
    "title": "세계 1위 티띠꾼, 이변 없이 고국 태국서 우승…김효주는 단독 3위",
    "partialText": "",
    "date": "2026-02-22T18:10:31.000Z",
    "url": "https://www.sedaily.com/article/20011135"
  },
  {
    "publisherId": "sedaily",
    "publisherName": "서울경제",
    "specTitle": "스포츠",
    "categories": [
      "sports"
    ],
    "specUrl": "https://www.sedaily.com/rss/sports",
    "title": "설상 강국 노르웨이, 종합 1위 확정…크로스컨트리 클레보 6관왕",
    "partialText": "",
    "date": "2026-02-22T17:10:57.000Z",
    "url": "https://www.sedaily.com/article/20011066"
  },
  {
    "publisherId": "sedaily",
    "publisherName": "서울경제",
    "specTitle": "스포츠",
    "categories": [
      "sports"
    ],
    "specUrl": "https://www.sedaily.com/rss/sports",
    "title": "2030 프랑스올림픽 스피드 스케이팅, 비개최국서 열린다",
    "partialText": "",
    "date": "2026-02-22T16:23:40.000Z",
    "url": "https://www.sedaily.com/article/20011058"
  },
  {
    "publisherId": "sedaily",
    "publisherName": "서울경제",
    "specTitle": "스포츠",
    "categories": [
      "sports"
    ],
    "specUrl": "https://www.sedaily.com/rss/sports",
    "title": "손흥민 ‘메손매치’ MLS 개막전서 도움…LAFC 3-0 완승",
    "partialText": "",
    "date": "2026-02-22T16:23:07.000Z",
    "url": "https://www.sedaily.com/article/20011056"
  },
  {
    "publisherId": "sedaily",
    "publisherName": "서울경제",
    "specTitle": "스포츠",
    "categories": [
      "sports"
    ],
    "specUrl": "https://www.sedaily.com/rss/sports",
    "title": "밀라노서 날아 오른 김길리·최가온 ‘Z세대’…4년 뒤 알프스가 더 기대된다[밀라노 코르티나 2026]",
    "partialText": "",
    "date": "2026-02-22T16:22:54.000Z",
    "url": "https://www.sedaily.com/article/20011055"
  },
  {
    "publisherId": "sedaily",
    "publisherName": "서울경제",
    "specTitle": "스포츠",
    "categories": [
      "sports"
    ],
    "specUrl": "https://www.sedaily.com/rss/sports",
    "title": "음주운전 징계 뒤 ‘헝가리 귀화’ 김민석 “한국 사랑했지만, 스케이트를 더 사랑”",
    "partialText": "",
    "date": "2026-02-22T13:53:58.000Z",
    "url": "https://www.sedaily.com/article/20011032"
  },
  {
    "publisherId": "sedaily",
    "publisherName": "서울경제",
    "specTitle": "스포츠",
    "categories": [
      "sports"
    ],
    "specUrl": "https://www.sedaily.com/rss/sports",
    "title": "셰플러, 우즈 넘고 ‘9연속 톱4’ 기록 작성할까…매킬로이는 6타 차 역전 우승 도전",
    "partialText": "",
    "date": "2026-02-22T13:43:05.000Z",
    "url": "https://www.sedaily.com/article/20011028"
  },
  {
    "publisherId": "sedaily",
    "publisherName": "서울경제",
    "specTitle": "스포츠",
    "categories": [
      "sports"
    ],
    "specUrl": "https://www.sedaily.com/rss/sports",
    "title": "이강인, 부상 복귀 후 첫 선발 출전…날카로운 패스로 대승 견인",
    "partialText": "",
    "date": "2026-02-22T10:14:47.000Z",
    "url": "https://www.sedaily.com/article/20010986"
  },
  {
    "publisherId": "sedaily",
    "publisherName": "서울경제",
    "specTitle": "스포츠",
    "categories": [
      "sports"
    ],
    "specUrl": "https://www.sedaily.com/rss/sports",
    "title": "‘장거리 간판’ 정재원, 매스스타트서 5위…韓 빙속 24년 만의 ‘노 메달’[밀라노 코르티나 2026]",
    "partialText": "",
    "date": "2026-02-22T07:49:51.000Z",
    "url": "https://www.sedaily.com/article/20010975"
  }
]